matplottery/__init__.py
matplottery/braille.py
matplottery/plotter.py
matplottery/utils.py
matplottery-1.0.6.dist-info/METADATA
matplottery-1.0.6.dist-info/WHEEL
matplottery-1.0.6.dist-info/top_level.txt
matplottery-1.0.6.dist-info/RECORD
