Metadata-Version: 2.1
Name: matplottery
Version: 1.0.6
Summary: Nicer histograms with numpy and plotting with matplotlib
Home-page: https://github.com/aminnj/matplottery
Author: Nick Amin
Author-email: amin.nj@gmail.com
License: UNKNOWN
Platform: UNKNOWN
Classifier: License :: OSI Approved :: MIT License
Classifier: Programming Language :: Python :: 2.7
Requires-Dist: matplotlib (>2.0)
Requires-Dist: numpy
Requires-Dist: uproot (>3.0)
